deprem_ocr/__init__.py
deprem_ocr/detector.py
deprem_ocr/ocr.py
deprem_ocr/recognizer.py
deprem_ocr/utility.py
deprem_ocr/ch_PP-OCRv3_det_infer/inference.pdiparams
deprem_ocr/ch_PP-OCRv3_det_infer/inference.pdiparams.info
deprem_ocr/ch_PP-OCRv3_det_infer/inference.pdmodel
deprem_ocr/ch_PP-OCRv3_rec_infer/inference.pdiparams
deprem_ocr/ch_PP-OCRv3_rec_infer/inference.pdiparams.info
deprem_ocr/ch_PP-OCRv3_rec_infer/inference.pdmodel
deprem_ocr/postprocess/__init__.py
deprem_ocr/postprocess/cls_postprocess.py
deprem_ocr/postprocess/db_postprocess.py
deprem_ocr/postprocess/east_postprocess.py
deprem_ocr/postprocess/extract_textpoint_fast.py
deprem_ocr/postprocess/extract_textpoint_slow.py
deprem_ocr/postprocess/fce_postprocess.py
deprem_ocr/postprocess/locality_aware_nms.py
deprem_ocr/postprocess/pg_postprocess.py
deprem_ocr/postprocess/poly_nms.py
deprem_ocr/postprocess/rec_postprocess.py
deprem_ocr/postprocess/sast_postprocess.py
deprem_ocr/postprocess/vqa_token_re_layoutlm_postprocess.py
deprem_ocr/postprocess/vqa_token_ser_layoutlm_postprocess.py
deprem_ocr/postprocess/pse_postprocess/__init__.py
deprem_ocr/postprocess/pse_postprocess/pse_postprocess.py
deprem_ocr/postprocess/pse_postprocess/pse/__init__.py
deprem_ocr/postprocess/pse_postprocess/pse/setup.py
deprem_ocr/ppocr/__init__.py
deprem_ocr/ppocr/ppocr_keys_v1.txt
deprem_ocr/ppocr/data/__init__.py
deprem_ocr/ppocr/data/collate_fn.py
deprem_ocr/ppocr/data/lmdb_dataset.py
deprem_ocr/ppocr/data/pgnet_dataset.py
deprem_ocr/ppocr/data/pubtab_dataset.py
deprem_ocr/ppocr/data/simple_dataset.py
deprem_ocr/ppocr/data/imaug/ColorJitter.py
deprem_ocr/ppocr/data/imaug/__init__.py
deprem_ocr/ppocr/data/imaug/copy_paste.py
deprem_ocr/ppocr/data/imaug/east_process.py
deprem_ocr/ppocr/data/imaug/fce_aug.py
deprem_ocr/ppocr/data/imaug/fce_targets.py
deprem_ocr/ppocr/data/imaug/gen_table_mask.py
deprem_ocr/ppocr/data/imaug/iaa_augment.py
deprem_ocr/ppocr/data/imaug/label_ops.py
deprem_ocr/ppocr/data/imaug/make_border_map.py
deprem_ocr-1.0.19.dist-info/LICENSE
deprem_ocr-1.0.19.dist-info/METADATA
deprem_ocr-1.0.19.dist-info/WHEEL
deprem_ocr-1.0.19.dist-info/top_level.txt
deprem_ocr-1.0.19.dist-info/RECORD
