Metadata-Version: 2.1
Name: deprem-ocr
Version: 1.0.19
Summary: Extract texts from images and screenshots
Home-page: https://github.com/Goodsea/deprem-ocr
Author: Kutsal Ozkurt
Author-email: kutsal_baran@hotmail.com
Project-URL: Bug Tracker, https://github.com/Goodsea/deprem-ocr/issues
Classifier: Programming Language :: Python :: 3
Classifier: License :: OSI Approved :: MIT License
Classifier: Operating System :: OS Independent
Requires-Python: >=3.8
License-File: LICENSE
